acequia/__init__.py
acequia/gwcollection.py
acequia/gwlist.py
acequia/gwlocs.py
acequia/gwseries.py
acequia/headsdif.py
acequia/swseries.py
acequia/version.py
acequia/geo/__init__.py
acequia/geo/coordinate_conversion.py
acequia/geo/pointshapewriter.py
acequia/geo/waypoint_kml.py
acequia/plots/__init__.py
acequia/plots/plotfun.py
acequia/plots/plotheads.py
acequia/plots/tsmodelstatsplot.py
acequia/read/__init__.py
acequia/read/brogldxml.py
acequia/read/brogmwxml.py
acequia/read/brorest.py
acequia/read/dawaco.py
acequia/read/dinogws.py
acequia/read/dinosurfacelevel.py
acequia/read/filedirtools.py
acequia/read/gpxtree.py
acequia/read/gwfiles.py
acequia/read/hydromonitor.py
acequia/read/knmi_download.py
acequia/read/knmi_rain.py
acequia/read/knmi_weather.py
acequia/read/waterweb.py
acequia/read/waterwebtools.py
acequia/stats/__init__.py
acequia/stats/gwliststats.py
acequia/stats/gwtimestats.py
acequia/stats/gxg.py
acequia/stats/meteo_drought.py
acequia/stats/quantiles.py
acequia/stats/utils.py
acequia-0.1.5.dist-info/METADATA
acequia-0.1.5.dist-info/WHEEL
acequia-0.1.5.dist-info/top_level.txt
acequia-0.1.5.dist-info/RECORD
