Metadata-Version: 2.1
Name: acequia
Version: 0.1.5
Summary: Python package for reading, writing and analyzinggroundwater head time series.
Home-page: https://github.com/acequia-package/acequia.git
Author: T.J. de Meij
Author-email: thomasdemeij@gmail.com
License: MIT
Requires-Dist: numpy
Requires-Dist: matplotlib
Requires-Dist: scipy
Requires-Dist: pandas
Requires-Dist: geopandas
Requires-Dist: shapely
Requires-Dist: seaborn
Requires-Dist: statsmodels
Requires-Dist: simplekml
Requires-Dist: sphinx
